retrieval/__init__.py
retrieval/convert_dataset_to_jsonl.py
retrieval/elastic_reranking_retriever.py
retrieval/elastic_retriever.py
retrieval/pyserini_retrieval.py
retrieval/retriever.py
retrieval/test.py
retrieval/utils.py
retrieval/write_dataset.py
retrieval/bert_reranker/__init__.py
retrieval/bert_reranker/bert_reranking_retriever.py
retrieval/bert_reranker/inference.py
retrieval/bert_reranker/inference_dataset.py
cosmos_retrieve-0.1.dist-info/LICENSE
cosmos_retrieve-0.1.dist-info/METADATA
cosmos_retrieve-0.1.dist-info/WHEEL
cosmos_retrieve-0.1.dist-info/top_level.txt
cosmos_retrieve-0.1.dist-info/RECORD
